vapory/__init__.py
vapory/config.py
vapory/helpers.py
vapory/io.py
vapory/vapory.py
vapory/version.py
Vapory-0.1.2.dist-info/LICENSE.txt
Vapory-0.1.2.dist-info/METADATA
Vapory-0.1.2.dist-info/WHEEL
Vapory-0.1.2.dist-info/top_level.txt
Vapory-0.1.2.dist-info/RECORD
