Metadata-Version: 2.1
Name: Vapory
Version: 0.1.2
Summary: 3D rendering with Python and POV-Ray
Home-page: UNKNOWN
Author: Zulko
License: see LICENSE.txt
Keywords: 3D POV-Ray Photo-realistic ray-tracing
Platform: UNKNOWN
